{"id":"E0240AF6-6335-43EA-B7AA-FC17C52B511D","validationEntity":{"analysedDataType":"auto","dataResult":{"createdDate":"2022-01-10T08:43:06Z"}},"modelEntity":{"createdDate":"2022-01-10T08:43:06Z","id":"68DD35D6-80E3-4D32-9052-5E1AB8A969A9","experimentID":"8529592E-C521-45FF-974D-11019588A888","title":"","modifiedDate":"2022-01-10T08:43:06Z","preferredFilename":"","version":"1.0","modelURL":"Models\/BetterRest%201%20copy.mlmodel"},"version":"1.0","settingEntity":{"augmentations":[],"suggestedColumns":["wake","estimatedSleep","coffee","actualSleep"],"targetColumn":"actualSleep","seedType":"default","transferLearningEmbeddingType":"dynamic","handPoseClassifierAugmentations":[],"featureNames":["wake","estimatedSleep","coffee"],"algorithmType":"maxEnt","harVideoAugmentations":0,"taskType":"generalRegresor","suggestedColumnValues":["31 500, 32 400, 26 100, 40 500, 19 800, 27 000, 20 700, 21 600, 41 400, 34 200, 21 600, 78 300, 32 400, 28 800, 18 900, 18 000, 28 800, 18 000, 7 200, 35 100, 24 300, 35 100, 34 200, 27 900, 30 600, 69 300, 35 100, 34 200, 34 200, 23 400","9,00, 5,00, 6,50, 8,75, 6,00, 7,50, 9,25, 6,00, 9,25, 6,75, 5,25, 9,25, 10,00, 8,75, 8,25, 6,25, 10,00, 6,25, 10,00, 9,50, 5,00, 7,50, 6,25, 8,00, 8,00, 6,50, 8,00, 10,00, 8,25, 8,00","6, 2, 10, 4, 3, 1, 1, 3, 5, 8, 3, 8, 2, 3, 1, 2, 3, 2, 1, 4, 2, 1, 1, 4, 3, 7, 4, 4, 1, 3","38 230, 20 180, 31 989, 35 258, 24 487, 28 300, 34 548, 24 557, 37 836, 31 340, 21 874, 40 405, 38 076, 34 265, 30 936, 24 665, 39 007, 24 578, 37 267, 37 878, 20 220, 28 400, 23 882, 32 427, 31 699, 29 670, 32 789, 39 792, 30 935, 31 701"],"handActionClassifierAugmentations":[],"suggestedColumnTypes":["Int","Double","Int","Int"],"generalRegressorType":{"boostedTree":{"stepSize":0.29999999999999999,"rowSubsample":1,"columnSubsample":1,"minLossReduction":0,"minChildWeight":0.10000000000000001,"maxDepth":6}},"styleTransferAlgorithmType":"image","iterationCount":10},"state":"trained","trainingEntity":{"finishTime":"2022-01-10T08:43:25Z","recipeTrainingResults":{"generalRegressor":{"maximumError":2711.96484375,"rootMeanSquaredError":910.95785820760091}},"dataResult":{"itemsCount":10000,"createdDate":"2022-01-10T08:43:06Z","dataURL":"file:\/\/\/Users\/paul-louisrenard\/Downloads\/HackingWithSwift-main\/SwiftUI\/project4-files\/BetterRest.csv","columnTypes":["Int","Double","Int","Int"],"analysis":{"summary":{"canUseValidation":1,"sampleCount":10000},"issues":[{"description":"Data has 10000 rows","severity":"info"}],"regressorAnalysis":{"targetRange":[19216,45224]}},"dataSourceID":"4F8507FA-70DB-42C3-85D5-3EC87642E396","columns":["wake","estimatedSleep","coffee","actualSleep"],"columnValues":["31 500, 32 400, 26 100, 40 500, 19 800, 27 000, 20 700, 21 600, 41 400, 34 200, 21 600, 78 300, 32 400, 28 800, 18 900, 18 000, 28 800, 18 000, 7 200, 35 100, 24 300, 35 100, 34 200, 27 900, 30 600, 69 300, 35 100, 34 200, 34 200, 23 400","9,00, 5,00, 6,50, 8,75, 6,00, 7,50, 9,25, 6,00, 9,25, 6,75, 5,25, 9,25, 10,00, 8,75, 8,25, 6,25, 10,00, 6,25, 10,00, 9,50, 5,00, 7,50, 6,25, 8,00, 8,00, 6,50, 8,00, 10,00, 8,25, 8,00","6, 2, 10, 4, 3, 1, 1, 3, 5, 8, 3, 8, 2, 3, 1, 2, 3, 2, 1, 4, 2, 1, 1, 4, 3, 7, 4, 4, 1, 3","38 230, 20 180, 31 989, 35 258, 24 487, 28 300, 34 548, 24 557, 37 836, 31 340, 21 874, 40 405, 38 076, 34 265, 30 936, 24 665, 39 007, 24 578, 37 267, 37 878, 20 220, 28 400, 23 882, 32 427, 31 699, 29 670, 32 789, 39 792, 30 935, 31 701"],"targetRange":[19216,45224]},"dataURL":"file:\/\/\/Users\/paul-louisrenard\/Downloads\/HackingWithSwift-main\/SwiftUI\/project4-files\/BetterRest.csv","featureExtractionCheckpointMayBeAvailable":false,"recipeValidationResults":{"generalRegressor":{"maximumError":2415.203125,"rootMeanSquaredError":927.00140460254613}},"progress":[],"trainingAccuracy":910.95785820760091,"checkpointMetrics":{},"analysedDataType":"none","dataSourceID":"4F8507FA-70DB-42C3-85D5-3EC87642E396","snapshottableCheckpoints":{},"validationAccuracy":927.00140460254613,"startTime":"2022-01-10T08:43:25Z"},"createdDate":"2022-01-10T08:43:06Z","evaluationContainerEntity":{"testingEvaluationEntity":{"id":"39adc268-3029-4ba6-9b62-1251bb7bcae2","createdDate":"2022-01-10T08:43:06Z","dataResult":{"createdDate":"2022-01-10T08:43:06Z"},"analysedDataType":"none"},"createdDate":"2022-01-10T08:43:29Z","id":"6b84da58-13ef-4aad-ac9c-24e1f3b366dd","trainingEvaluationEntity":{"result":{"generalRegressor":{"maximumError":2711.96484375,"rootMeanSquaredError":910.95785820760091}},"createdDate":"2022-01-10T08:43:06Z","id":"365c70a1-5a33-4fbc-b105-6b3be56080cb","dataURL":"file:\/\/\/Users\/paul-louisrenard\/Downloads\/HackingWithSwift-main\/SwiftUI\/project4-files\/BetterRest.csv","dataSourceID":"4F8507FA-70DB-42C3-85D5-3EC87642E396","dataResult":{"itemsCount":10000,"createdDate":"2022-01-10T08:43:06Z","targetRange":[19216,45224],"dataURL":"file:\/\/\/Users\/paul-louisrenard\/Downloads\/HackingWithSwift-main\/SwiftUI\/project4-files\/BetterRest.csv","dataSourceID":"4F8507FA-70DB-42C3-85D5-3EC87642E396","analysis":{"summary":{"canUseValidation":1,"sampleCount":10000},"issues":[{"description":"Data has 10000 rows","severity":"info"}],"regressorAnalysis":{"targetRange":[19216,45224]}}},"analysedDataType":"none"},"previewType":"tabularRegressor","modifiedDate":"2022-01-10T08:43:29Z","validationEvaluationEntity":{"result":{"generalRegressor":{"maximumError":2415.203125,"rootMeanSquaredError":927.00140460254613}},"id":"29740745-9ec7-424a-ad23-e4433f475dee","createdDate":"2022-01-10T08:43:06Z","dataResult":{"createdDate":"2022-01-10T08:43:06Z"},"analysedDataType":"auto"},"evaluationEntities":[{"id":"7f383d65-02ee-400c-b8c1-9d2fd2685ed9","createdDate":"2022-01-10T08:43:29Z","dataResult":{},"analysedDataType":"none"}]},"evaluationEntities":[],"activityEntities":["trainingFinished",[{"id":"57DE52E8-C4F4-4EED-9108-A82014D25741","title":"Training Completed","createdDate":"2022-01-10T08:43:25Z","event":"trainingFinished","subtitle":"10 iterations"}],"trainingStarted",[{"id":"E935DB3E-FC6B-4948-AAF3-3467D0A7C45E","title":"Training Started","createdDate":"2022-01-10T08:43:25Z","event":"trainingStarted","subtitle":"10 iterations"}],"experimentCreated",[{"id":"B568E2F0-FFA9-4E41-979A-E33374A01FE9","title":"Model Source Created","createdDate":"2022-01-10T08:43:06Z","event":"experimentCreated","subtitle":"BetterRest 1 copy"}]],"title":"BetterRest 1 copy","evaluationEntity":{"id":"a29866d3-b210-4a30-bfd4-e05084f0c560","createdDate":"2022-01-10T08:43:06Z","dataResult":{"createdDate":"2022-01-10T08:43:06Z"},"analysedDataType":"none"},"evaluationState":"uninitialized","snapshotRole":{"withoutSnapshots":0},"modifiedDate":"2022-01-10T08:43:29Z","contentDataResult":{"createdDate":"2022-01-10T08:36:23Z"},"preferredFilename":"BetterRest 1 copy"}